bruinen/__init__.py
bruinen/client/__init__.py
bruinen/client/api/__init__.py
bruinen/client/api/accounts/__init__.py
bruinen/client/api/accounts/account_counts_for_policy.py
bruinen/client/api/accounts/accounts_controller_deactivate.py
bruinen/client/api/accounts/accounts_controller_get_accounts.py
bruinen/client/api/accounts/find_all_accounts_for_user.py
bruinen/client/api/accounts/find_all_active_for_user.py
bruinen/client/api/accounts/find_all_active_with_policy_for_user.py
bruinen/client/api/accounts/get_account.py
bruinen/client/api/auth/__init__.py
bruinen/client/api/auth/get_user_auth_token.py
bruinen/client/api/confirm/__init__.py
bruinen/client/api/confirm/create.py
bruinen/client/api/confirm/find_one.py
bruinen/client/api/connection_requests/__init__.py
bruinen/client/api/connection_requests/connection_requests_controller_find_all.py
bruinen/client/api/connection_requests/create.py
bruinen/client/api/connection_requests/get.py
bruinen/client/api/source_policy/__init__.py
bruinen/client/api/source_policy/source_policy_controller_get_all_active_for_client.py
bruinen/client/api/source_policy/source_policy_controller_get_defaults_for_client.py
bruinen/client/api/source_policy/source_policy_controller_get_policy_by_id.py
bruinen/client/api/source_policy/source_policy_controller_set_default.py
bruinen/client/api/sources/__init__.py
bruinen/client/api/sources/github_controller_profile.py
bruinen/client/api/sources/github_controller_repos.py
bruinen/client/api/sources/google_controller_calendar.py
bruinen/client/api/sources/google_controller_calendars.py
bruinen/client/api/sources/google_controller_draft.py
bruinen/client/api/sources/google_controller_drafts.py
bruinen/client/api/sources/google_controller_event.py
bruinen/client/api/sources/google_controller_events.py
bruinen/client/api/sources/google_controller_label.py
bruinen/client/api/sources/google_controller_labels.py
bruinen/client/api/sources/google_controller_message.py
bruinen-1.2.1.dist-info/METADATA
bruinen-1.2.1.dist-info/WHEEL
bruinen-1.2.1.dist-info/RECORD
